{
  "HOMELESS_ID": "92bb5efa-8559-40d4-bd6c-37dbe403bace",
  "BIRTHDAY": "1983-04-10",
  "COMMENTS": [
        {
          "COMMENT_AVANTAR": "https://img95.699pic.com/xsj/08/wg/1v.jpg%21/fh/300",
          "COMMENT_TAG": "Healthcare",
          "COMMENT_TIME": "2022-10-14 22:47:05",
          "COMMENT_USER": "Ruta",
          "COMMENT_ORG": "Apple"
        }
        ,
        {
          "COMMENT_AVANTAR": "https://img95.699pic.com/xsj/08/wg/1v.jpg%21/fh/300",
          "COMMENT_TAG": "Healthcare",
          "COMMENT_TIME": "2023-03-21 22:47:05",
          "COMMENT_USER": "Oaklee",
          "COMMENT_ORG": "Amazon"
        }
        ,
        {
          "COMMENT_AVANTAR": "https://img95.699pic.com/xsj/08/wg/1v.jpg%21/fh/300",
          "COMMENT_TAG": "Addiction Treatment",
          "COMMENT_TIME": "2024-05-14 22:47:05",
          "COMMENT_USER": "Harper",
          "COMMENT_ORG": "Addiction Treatment Center"
        }
  ],
  "ENTER_DATE": "2023-01-08 22:47:05",
  "ENTER_USER": "SYSTEM",
  "IMAGE": "https://img95.699pic.com/xsj/08/wg/1v.jpg%21/fh/300",
  "JOIN_DATE": "2024-01-24",
  "NAME": "Hazel",
  "ORG6": true,
  "ORG3": true,
  "ORG5": true,
  "SERVICE3": true,
  "SERVICE4": true,
  "ORG_SERVICE": {
      "ORG3": {
          "ORG_NAME": "Amazon",
          "SERVICE3": {
              "SERVICE_NAME": "Healthcare",
              "START_DATE": "2023-10-25",
              "PROGRESS_DETAIL": [
                  {
                      "DESC": "Work on phase3",
                      "TIME": "2023-10-11 22:47:05"
                  }
              ],
              "END_DATE": "2023-12-01"
          }
      }
      ,
      "ORG5": {
          "ORG_NAME": "Addiction Treatment Center",
          "SERVICE4": {
              "SERVICE_NAME": "Addiction Treatment",
              "START_DATE": "2024-01-21",
              "PROGRESS_DETAIL": [
                  {
                      "DESC": "Work on phase5",
                      "TIME": "2023-09-27 22:47:05"
                  }
                  ,
                  {
                      "DESC": "Work on phase5",
                      "TIME": "2023-09-07 22:47:05"
                  }
                  ,
                  {
                      "DESC": "Work on phase5",
                      "TIME": "2023-01-26 22:47:05"
                  }
              ],
              "END_DATE": "2024-03-16"
          }
      }
      ,
      "ORG6": {
          "ORG_NAME": "Apple",
          "SERVICE3": {
              "SERVICE_NAME": "Healthcare",
              "START_DATE": "2024-02-28",
              "PROGRESS_DETAIL": [
                  {
                      "DESC": "Work on phase1",
                      "TIME": "2024-03-14 22:47:05"
                  }
                  ,
                  {
                      "DESC": "Work on phase1",
                      "TIME": "2023-03-03 22:47:05"
                  }
                  ,
                  {
                      "DESC": "Work on phase3",
                      "TIME": "2024-02-02 22:47:05"
                  }
                  ,
                  {
                      "DESC": "Work on phase3",
                      "TIME": "2022-11-19 22:47:05"
                  }
                  ,
                  {
                      "DESC": "Work on phase5",
                      "TIME": "2022-09-28 22:47:05"
                  }
              ],
              "END_DATE": "2023-12-10"
          }
      }
  },
  "PERMANENT_DATE": "",
  "PHONE": "18369278586",
  "REQUEST": "Need food",
  "STATUS": "ASSIGNED"
}
